LICENSE.rst
flask_identity/__init__.py
flask_identity/_hash_context.py
flask_identity/_token_context.py
flask_identity/babels.py
flask_identity/compats.py
flask_identity/config.py
flask_identity/core.py
flask_identity/datastore.py
flask_identity/decorators.py
flask_identity/forms.py
flask_identity/mixins.py
flask_identity/translations/en_US/LC_MESSAGES/flask_identity.mo
flask_identity/translations/en_US/LC_MESSAGES/flask_identity.po
flask_identity/translations/flask_identity.pot
flask_identity/translations/zh_hans_CN/LC_MESSAGES/flask_identity.mo
flask_identity/translations/zh_hans_CN/LC_MESSAGES/flask_identity.po
flask_identity/utils.py
flask_identity/views.py
flask_identity-1.0.6.dist-info/LICENSE.rst
flask_identity-1.0.6.dist-info/METADATA
flask_identity-1.0.6.dist-info/WHEEL
flask_identity-1.0.6.dist-info/RECORD
