Metadata-Version: 2.1
Name: flask-identity
Version: 1.0.6
Summary: A lightweight extension & library to security Flask applications quickly and simply.
Home-page: https://github.com/SolardiaX/flask-identity
License: MIT
Author: SolardiaX
Author-email: solardiax@hotmail.com
Maintainer: SolardiaX
Maintainer-email: solardiax@hotmail.com
Requires-Python: >=3.9,<4.0
Classifier: Development Status :: 4 - Beta
Classifier: Environment :: Web Environment
Classifier: Framework :: Flask
Classifier: Intended Audience :: Developers
Classifier: License :: OSI Approved :: MIT License
Classifier: Operating System :: OS Independent
Classifier: Programming Language :: Python
Classifier: Programming Language :: Python :: 3
Classifier: Programming Language :: Python :: 3.9
Classifier: Programming Language :: Python :: 3.10
Classifier: Programming Language :: Python :: 3.11
Classifier: Programming Language :: Python :: Implementation :: CPython
Classifier: Programming Language :: Python :: Implementation :: PyPy
Classifier: Topic :: Internet :: WWW/HTTP :: Dynamic Content
Classifier: Topic :: Security
Classifier: Topic :: Software Development :: Libraries
Classifier: Topic :: Software Development :: Libraries :: Python Modules
Classifier: Topic :: Utilities
Requires-Dist: bcrypt (>=4.0.1,<5.0.0)
Requires-Dist: cryptography (>=41.0.0,<42.0.0)
Requires-Dist: flask (>=2.3.2,<3.0.0)
Requires-Dist: flask-babel (>=3.1.0,<4.0.0)
Requires-Dist: flask-wtf (>=1.1.1,<2.0.0)
Requires-Dist: passlib (>=1.7.4,<2.0.0)
Project-URL: Repository, https://github.com/SolardiaX/flask-identity
